implementation/__init__.py
implementation/extensionRemover.py
implementation/main.py
removeOaExtension-0.0.6.dist-info/LICENSE
removeOaExtension-0.0.6.dist-info/METADATA
removeOaExtension-0.0.6.dist-info/WHEEL
removeOaExtension-0.0.6.dist-info/entry_points.txt
removeOaExtension-0.0.6.dist-info/top_level.txt
removeOaExtension-0.0.6.dist-info/RECORD
