Metadata-Version: 2.1
Name: removeOaExtension
Version: 0.0.6
Summary: Tool to remove vendor extension from OpenAPI documents
Home-page: https://github.com/JoaoCamposFrom94/OpenAPI-extension-remover
Author: João Campos
Author-email: camposOnAi@gmail.com
License: UNKNOWN
Platform: UNKNOWN
Classifier: Development Status :: 3 - Alpha
Classifier: Intended Audience :: Developers
Classifier: Programming Language :: Python :: 3
Classifier: License :: OSI Approved :: GNU Affero General Public License v3
Classifier: Operating System :: OS Independent
Requires-Dist: PyYAML (>=3.13)
